cygwinreg3/__init__.py
cygwinreg3/constants.py
cygwinreg3/w32api.py
cygwinreg3-1.2.dist-info/LICENSE.txt
cygwinreg3-1.2.dist-info/METADATA
cygwinreg3-1.2.dist-info/WHEEL
cygwinreg3-1.2.dist-info/top_level.txt
cygwinreg3-1.2.dist-info/RECORD
